{"abstract":null,"action":null,"agencies":[{"raw_name":"EXECUTIVE OFFICE OF THE PRESIDENT","name":"Executive Office of the President","id":538,"url":"https://www.federalregister.gov/agencies/executive-office-of-the-president","json_url":"https://www.federalregister.gov/api/v1/agencies/538","parent_id":null,"slug":"executive-office-of-the-president"}],"body_html_url":"https://www.federalregister.gov/documents/full_text/html/2010/12/29/2010-32960.html","cfr_references":[],"citation":"75 FR 81817","comment_url":null,"comments_close_on":null,"correction_of":null,"corrections":[],"dates":null,"disposition_notes":null,"docket_ids":[],"document_number":"2010-32960","effective_on":null,"end_page":81828,"executive_order_notes":null,"executive_order_number":"13561","full_text_xml_url":"https://www.federalregister.gov/documents/full_text/xml/2010/12/29/2010-32960.xml","html_url":"https://www.federalregister.gov/documents/2010/12/29/2010-32960/adjustments-of-certain-rates-of-pay","images":{"OB#1.EPS":{"large":"https://images.federalregister.gov/OB%231.EPS/large.png?1278291883","original":"https://images.federalregister.gov/OB%231.EPS/original.png?1278291883"},"ED29DE10.027":{"large":"https://images.federalregister.gov/ED29DE10.027/large.png?1479493919","original":"https://images.federalregister.gov/ED29DE10.027/original.png?1479493919"},"ED29DE10.028":{"large":"https://images.federalregister.gov/ED29DE10.028/large.png?1479493923","original":"https://images.federalregister.gov/ED29DE10.028/original.png?1479493923"},"ED29DE10.029":{"large":"https://images.federalregister.gov/ED29DE10.029/large.png?1479493927","original":"https://images.federalregister.gov/ED29DE10.029/original.png?1479493927"},"ED29DE10.030":{"large":"https://images.federalregister.gov/ED29DE10.030/large.png?1479493933","original":"https://images.federalregister.gov/ED29DE10.030/original.png?1479493933"},"ED29DE10.031":{"large":"https://images.federalregister.gov/ED29DE10.031/large.png?1479493938","original":"https://images.federalregister.gov/ED29DE10.031/original.png?1479493938"},"ED29DE10.032":{"large":"https://images.federalregister.gov/ED29DE10.032/large.png?1479493944","original":"https://images.federalregister.gov/ED29DE10.032/original.png?1479493944"},"ED29DE10.033":{"large":"https://images.federalregister.gov/ED29DE10.033/large.png?1479493950","original":"https://images.federalregister.gov/ED29DE10.033/original.png?1479493950"},"ED29DE10.034":{"large":"https://images.federalregister.gov/ED29DE10.034/large.png?1479493954","original":"https://images.federalregister.gov/ED29DE10.034/original.png?1479493954"},"ED29DE10.035":{"large":"https://images.federalregister.gov/ED29DE10.035/large.png?1479493958","original":"https://images.federalregister.gov/ED29DE10.035/original.png?1479493958"},"ED29DE10.036":{"large":"https://images.federalregister.gov/ED29DE10.036/large.png?1479493960","original":"https://images.federalregister.gov/ED29DE10.036/original.png?1479493960"}},"json_url":"https://www.federalregister.gov/api/v1/documents/2010-32960?publication_date=2010-12-29","mods_url":"https://www.govinfo.gov/metadata/granule/FR-2010-12-29/2010-32960/mods.xml","page_length":12,"page_views":{"count":359,"last_updated":"2020-11-28 16:15:09 -0500"},"pdf_url":"https://www.govinfo.gov/content/pkg/FR-2010-12-29/pdf/2010-32960.pdf","presidential_document_number":"13561","proclamation_number":null,"public_inspection_pdf_url":null,"publication_date":"2010-12-29","raw_text_url":"https://www.federalregister.gov/documents/full_text/text/2010/12/29/2010-32960.txt","regulation_id_number_info":{},"regulation_id_numbers":[],"regulations_dot_gov_info":{},"regulations_dot_gov_url":null,"significant":null,"signing_date":"2010-12-22","start_page":81817,"subtype":"Executive Order","title":"Adjustments of Certain Rates of Pay","toc_doc":"Rates of Pay; Adjustment (EO 13561)","toc_subject":"Government Agencies and Employees:","topics":[],"type":"Presidential Document","volume":75}